PyPiUpdateCheck/__init__.py
PyPiUpdateCheck/pypi_update_check.py
pypiupdatecheck-0.3.2.dist-info/METADATA
pypiupdatecheck-0.3.2.dist-info/WHEEL
pypiupdatecheck-0.3.2.dist-info/licenses/LICENSE.md
pypiupdatecheck-0.3.2.dist-info/RECORD
